shinny_structlog/__init__.py
shinny_structlog-0.0.4.dist-info/METADATA
shinny_structlog-0.0.4.dist-info/WHEEL
shinny_structlog-0.0.4.dist-info/top_level.txt
shinny_structlog-0.0.4.dist-info/RECORD
