Metadata-Version: 2.1
Name: shinny-structlog
Version: 0.0.4
Summary: Shinny StructLog
Home-page: https://github.com/shinnytech/structlog-python
Author: TianQin
Author-email: tianqincn@gmail.com
License: UNKNOWN
Platform: UNKNOWN
Classifier: Programming Language :: Python :: 3
Classifier: License :: OSI Approved :: Apache Software License
Requires-Python: >=3.6
